{
  "bounds": {
    "center": [
      -0.005818179,
      0.014986196,
      0.0039124996
    ],
    "size": [
      0.001,
      0.001,
      0.001
    ]
  },
  "primitives": [
    {
      "Box": {
        "center": [
          -0.005818179,
          0.014986196,
          0.0039124996
        ],
        "size": [
          0.001,
          0.001,
          0.001
        ]
      }
    },
    {
      "Sphere": {
        "center": [
          -0.005818179,
          0.014986196,
          0.0039124996
        ],
        "radius": 0.00017203916
      }
    },
    {
      "Cylinder": {
        "center": [
          -0.005818179,
          0.014986196,
          0.0039125
        ],
        "axis": "X",
        "radius": 0.0005,
        "height": 0.001
      }
    },
    {
      "Capsule": {
        "a": [
          -0.0059896326,
          0.014986196,
          0.0039125
        ],
        "b": [
          -0.005646725,
          0.014986196,
          0.0039125
        ],
        "radius": 0.00017190691
      }
    },
    {
      "Cylinder": {
        "center": [
          -0.005818179,
          0.014986196,
          0.0039125
        ],
        "axis": "Y",
        "radius": 0.0005,
        "height": 0.001
      }
    },
    {
      "Capsule": {
        "a": [
          -0.005818179,
          0.014814744,
          0.0039125
        ],
        "b": [
          -0.005818179,
          0.015157647,
          0.0039125
        ],
        "radius": 0.00017190876
      }
    },
    {
      "Cylinder": {
        "center": [
          -0.005818179,
          0.014986196,
          0.0039125
        ],
        "axis": "Z",
        "radius": 0.0005,
        "height": 0.001
      }
    },
    {
      "Capsule": {
        "a": [
          -0.005818179,
          0.014986196,
          0.0039
        ],
        "b": [
          -0.005818179,
          0.014986196,
          0.003925
        ],
        "radius": 0.00017158444
      }
    }
  ],
  "compounds": [
    {
      "partition_axis": "X",
      "parts": [
        {
          "center": [
            -0.005818179,
            0.014986196,
            0.0039
          ],
          "size": [
            0.001,
            0.001,
            0.001
          ]
        },
        {
          "center": [
            -0.005818179,
            0.014986196,
            0.0039124996
          ],
          "size": [
            0.001,
            0.001,
            0.001
          ]
        },
        {
          "center": [
            -0.005818179,
            0.014986196,
            0.003925
          ],
          "size": [
            0.001,
            0.001,
            0.001
          ]
        },
        {
          "center": [
            -0.0057324283,
            0.015071893,
            0.0039124996
          ],
          "size": [
            0.001,
            0.001,
            0.001
          ]
        }
      ],
      "quality": {
        "source_triangle_count": 232,
        "covered_triangle_count": 232,
        "conservative_volume": 4.0000008e-09,
        "bounds_volume_ratio": 4.0,
        "generation_path": "Exact"
      }
    }
  ],
  "convex_hull": {
    "points": [
      [
        -0.0059896326,
        0.014980085,
        0.0039
      ],
      [
        -0.0059896326,
        0.014980085,
        0.003925
      ],
      [
        -0.0059892978,
        0.014998444,
        0.0039
      ],
      [
        -0.0059892978,
        0.014998444,
        0.003925
      ],
      [
        -0.005988003,
        0.014961796,
        0.0039
      ],
      [
        -0.005988003,
        0.014961796,
        0.003925
      ],
      [
        -0.005987002,
        0.015016662,
        0.0039
      ],
      [
        -0.005987002,
        0.015016662,
        0.003925
      ],
      [
        -0.0059844274,
        0.014943786,
        0.0039
      ],
      [
        -0.0059844274,
        0.014943786,
        0.003925
      ],
      [
        -0.0059827715,
        0.01503453,
        0.0039
      ],
      [
        -0.0059827715,
        0.01503453,
        0.003925
      ],
      [
        -0.005978947,
        0.01492626,
        0.0039
      ],
      [
        -0.005978947,
        0.01492626,
        0.003925
      ],
      [
        -0.0059766555,
        0.015051844,
        0.0039
      ],
      [
        -0.0059766555,
        0.015051844,
        0.003925
      ],
      [
        -0.0059716245,
        0.014909422,
        0.0039
      ],
      [
        -0.0059716245,
        0.014909422,
        0.003925
      ],
      [
        -0.005968723,
        0.015068403,
        0.0039
      ],
      [
        -0.005968723,
        0.015068403,
        0.003925
      ],
      [
        -0.005962543,
        0.014893463,
        0.0039
      ],
      [
        -0.005962543,
        0.014893463,
        0.003925
      ],
      [
        -0.005959066,
        0.015084021,
        0.0039
      ],
      [
        -0.005959066,
        0.015084021,
        0.003925
      ],
      [
        -0.0059518083,
        0.014878566,
        0.0039
      ],
      [
        -0.0059518083,
        0.014878566,
        0.003925
      ],
      [
        -0.0059477948,
        0.015098516,
        0.0039
      ],
      [
        -0.0059477948,
        0.015098516,
        0.003925
      ],
      [
        -0.0059395423,
        0.014864902,
        0.0039
      ],
      [
        -0.0059395423,
        0.014864902,
        0.003925
      ],
      [
        -0.005935038,
        0.015111724,
        0.0039
      ],
      [
        -0.005935038,
        0.015111724,
        0.003925
      ],
      [
        -0.0059258854,
        0.014852628,
        0.0039
      ],
      [
        -0.0059258854,
        0.014852628,
        0.003925
      ],
      [
        -0.005920943,
        0.015123491,
        0.0039
      ],
      [
        -0.005920943,
        0.015123491,
        0.003925
      ],
      [
        -0.005910995,
        0.014841884,
        0.0039
      ],
      [
        -0.005910995,
        0.014841884,
        0.003925
      ],
      [
        -0.00590567,
        0.0151336845,
        0.0039
      ],
      [
        -0.00590567,
        0.0151336845,
        0.003925
      ],
      [
        -0.005895041,
        0.014832794,
        0.0039
      ],
      [
        -0.005895041,
        0.014832794,
        0.003925
      ],
      [
        -0.0058893953,
        0.015142187,
        0.0039
      ],
      [
        -0.0058893953,
        0.015142187,
        0.003925
      ],
      [
        -0.005878207,
        0.0148254605,
        0.0039
      ],
      [
        -0.005878207,
        0.0148254605,
        0.003925
      ],
      [
        -0.0058723046,
        0.0151489,
        0.0039
      ],
      [
        -0.0058723046,
        0.0151489,
        0.003925
      ],
      [
        -0.0058606854,
        0.01481997,
        0.0039
      ],
      [
        -0.0058606854,
        0.01481997,
        0.003925
      ],
      [
        -0.005854594,
        0.015153749,
        0.0039
      ],
      [
        -0.005854594,
        0.015153749,
        0.003925
      ],
      [
        -0.005842677,
        0.014816384,
        0.0039
      ],
      [
        -0.005842677,
        0.014816384,
        0.003925
      ],
      [
        -0.0058364673,
        0.015156675,
        0.0039
      ],
      [
        -0.0058364673,
        0.015156675,
        0.003925
      ],
      [
        -0.0058243885,
        0.014814744,
        0.0039
      ],
      [
        -0.0058243885,
        0.014814744,
        0.003925
      ],
      [
        -0.005818131,
        0.015157647,
        0.0039
      ],
      [
        -0.005818131,
        0.015157647,
        0.003925
      ],
      [
        -0.0058060293,
        0.014815068,
        0.0039
      ],
      [
        -0.0058060293,
        0.014815068,
        0.003925
      ],
      [
        -0.005800211,
        0.015156698,
        0.0039
      ],
      [
        -0.005800211,
        0.015156698,
        0.003925
      ],
      [
        -0.0057878103,
        0.014817352,
        0.0039
      ],
      [
        -0.0057878103,
        0.014817352,
        0.003925
      ],
      [
        -0.005782488,
        0.015153881,
        0.0039
      ],
      [
        -0.005782488,
        0.015153881,
        0.003925
      ],
      [
        -0.0057699396,
        0.014821572,
        0.0039
      ],
      [
        -0.0057699396,
        0.014821572,
        0.003925
      ],
      [
        -0.0057651564,
        0.015149228,
        0.0039
      ],
      [
        -0.0057651564,
        0.015149228,
        0.003925
      ],
      [
        -0.0057526226,
        0.014827678,
        0.0039
      ],
      [
        -0.0057526226,
        0.014827678,
        0.003925
      ],
      [
        -0.005748406,
        0.01514279,
        0.0039
      ],
      [
        -0.005748406,
        0.01514279,
        0.003925
      ],
      [
        -0.0057360576,
        0.014835601,
        0.0039
      ],
      [
        -0.0057360576,
        0.014835601,
        0.003925
      ],
      [
        -0.00573242,
        0.015134636,
        0.0039
      ],
      [
        -0.00573242,
        0.015134636,
        0.003925
      ],
      [
        -0.0057204347,
        0.014845248,
        0.0039
      ],
      [
        -0.0057204347,
        0.014845248,
        0.003925
      ],
      [
        -0.0057173735,
        0.0151248565,
        0.0039
      ],
      [
        -0.0057173735,
        0.0151248565,
        0.003925
      ],
      [
        -0.005705933,
        0.014856512,
        0.0039
      ],
      [
        -0.005705933,
        0.014856512,
        0.003925
      ],
      [
        -0.0057034316,
        0.015113559,
        0.0039
      ],
      [
        -0.0057034316,
        0.015113559,
        0.003925
      ],
      [
        -0.005692718,
        0.014869261,
        0.0039
      ],
      [
        -0.005692718,
        0.014869261,
        0.003925
      ],
      [
        -0.005690746,
        0.015100866,
        0.0039
      ],
      [
        -0.005690746,
        0.015100866,
        0.003925
      ],
      [
        -0.005680942,
        0.014883349,
        0.0039
      ],
      [
        -0.005680942,
        0.014883349,
        0.003925
      ],
      [
        -0.005679456,
        0.015086917,
        0.0039
      ],
      [
        -0.005679456,
        0.015086917,
        0.003925
      ],
      [
        -0.0056707393,
        0.014898615,
        0.0039
      ],
      [
        -0.0056707393,
        0.014898615,
        0.003925
      ],
      [
        -0.0056696855,
        0.015071864,
        0.0039
      ],
      [
        -0.0056696855,
        0.015071864,
        0.003925
      ],
      [
        -0.0056622275,
        0.014914885,
        0.0039
      ],
      [
        -0.0056622275,
        0.014914885,
        0.003925
      ],
      [
        -0.0056615416,
        0.015055873,
        0.0039
      ],
      [
        -0.0056615416,
        0.015055873,
        0.003925
      ],
      [
        -0.005655504,
        0.014931971,
        0.0039
      ],
      [
        -0.005655504,
        0.014931971,
        0.003925
      ],
      [
        -0.0056551127,
        0.01503912,
        0.0039
      ],
      [
        -0.0056551127,
        0.01503912,
        0.003925
      ],
      [
        -0.0056506456,
        0.014949679,
        0.0039
      ],
      [
        -0.0056506456,
        0.014949679,
        0.003925
      ],
      [
        -0.00565047,
        0.015021785,
        0.0039
      ],
      [
        -0.00565047,
        0.015021785,
        0.003925
      ],
      [
        -0.0056477077,
        0.014967805,
        0.0039
      ],
      [
        -0.0056477077,
        0.014967805,
        0.003925
      ],
      [
        -0.005647664,
        0.015004061,
        0.0039
      ],
      [
        -0.005647664,
        0.015004061,
        0.003925
      ],
      [
        -0.005646725,
        0.01498614,
        0.0039
      ],
      [
        -0.005646725,
        0.01498614,
        0.003925
      ]
    ]
  }
}
