{
  "bounds": {
    "center": [
      0.0039117336,
      0.015301825,
      0.003925
    ],
    "size": [
      0.001,
      0.0012378152,
      0.001
    ]
  },
  "primitives": [
    {
      "Box": {
        "center": [
          0.0039117336,
          0.015301825,
          0.003925
        ],
        "size": [
          0.001,
          0.0012378152,
          0.001
        ]
      }
    },
    {
      "Sphere": {
        "center": [
          0.0039117336,
          0.015301825,
          0.003925
        ],
        "radius": 0.0006310583
      }
    },
    {
      "Cylinder": {
        "center": [
          0.0039117336,
          0.015301825,
          0.003925
        ],
        "axis": "X",
        "radius": 0.00061941234,
        "height": 0.001
      }
    },
    {
      "Capsule": {
        "a": [
          0.0034348327,
          0.015301825,
          0.003925
        ],
        "b": [
          0.0043886346,
          0.015301825,
          0.003925
        ],
        "radius": 0.00061941234
      }
    },
    {
      "Cylinder": {
        "center": [
          0.0039117336,
          0.015301825,
          0.003925
        ],
        "axis": "Y",
        "radius": 0.0005,
        "height": 0.0012378152
      }
    },
    {
      "Capsule": {
        "a": [
          0.0039117336,
          0.014682917,
          0.003925
        ],
        "b": [
          0.0039117336,
          0.015920732,
          0.003925
        ],
        "radius": 0.0004775558
      }
    },
    {
      "Cylinder": {
        "center": [
          0.0039117336,
          0.015301825,
          0.003925
        ],
        "axis": "Z",
        "radius": 0.0006305629,
        "height": 0.001
      }
    },
    {
      "Capsule": {
        "a": [
          0.0039117336,
          0.015301825,
          0.0039
        ],
        "b": [
          0.0039117336,
          0.015301825,
          0.00395
        ],
        "radius": 0.0006305629
      }
    }
  ],
  "compounds": [
    {
      "partition_axis": "Y",
      "parts": [
        {
          "center": [
            0.0039117336,
            0.015301825,
            0.003925
          ],
          "size": [
            0.0010019074,
            0.0012397226,
            0.0010019074
          ]
        }
      ],
      "quality": {
        "source_triangle_count": 792,
        "covered_triangle_count": 792,
        "conservative_volume": 1.2444564e-09,
        "bounds_volume_ratio": 1.0053651,
        "generation_path": {
          "BoundsFallback": {
            "reason": {
              "PartitionLimit": {
                "connected_partition_count": 37,
                "maximum_exact_partitions": 32
              }
            }
          }
        }
      }
    }
  ],
  "convex_hull": {
    "points": [
      [
        0.0034348327,
        0.015088099,
        0.0039
      ],
      [
        0.0034348327,
        0.015088099,
        0.00395
      ],
      [
        0.003436366,
        0.015057705,
        0.0039
      ],
      [
        0.003436366,
        0.015057705,
        0.00395
      ],
      [
        0.0034421955,
        0.015016276,
        0.0039
      ],
      [
        0.0034421955,
        0.015016276,
        0.00395
      ],
      [
        0.0034522733,
        0.014975673,
        0.0039
      ],
      [
        0.0034522733,
        0.014975673,
        0.00395
      ],
      [
        0.0034664923,
        0.014936326,
        0.0039
      ],
      [
        0.0034664923,
        0.014936326,
        0.00395
      ],
      [
        0.0034807276,
        0.015589853,
        0.0039
      ],
      [
        0.0034807276,
        0.015589853,
        0.00395
      ],
      [
        0.0034810104,
        0.015609144,
        0.0039
      ],
      [
        0.0034810104,
        0.015609144,
        0.00395
      ],
      [
        0.0034813597,
        0.01556886,
        0.0039
      ],
      [
        0.0034813597,
        0.01556886,
        0.00395
      ],
      [
        0.0034840414,
        0.015637292,
        0.0039
      ],
      [
        0.0034840414,
        0.015637292,
        0.00395
      ],
      [
        0.0034844847,
        0.015540177,
        0.0039
      ],
      [
        0.0034844847,
        0.015540177,
        0.00395
      ],
      [
        0.0034847,
        0.01489866,
        0.0039
      ],
      [
        0.0034847,
        0.01489866,
        0.00395
      ],
      [
        0.0034897241,
        0.015665028,
        0.0039
      ],
      [
        0.0034897241,
        0.015665028,
        0.00395
      ],
      [
        0.003490686,
        0.015511998,
        0.0039
      ],
      [
        0.003490686,
        0.015511998,
        0.00395
      ],
      [
        0.0034980073,
        0.0156921,
        0.0039
      ],
      [
        0.0034980073,
        0.0156921,
        0.00395
      ],
      [
        0.0034998907,
        0.0154846525,
        0.0039
      ],
      [
        0.0034998907,
        0.0154846525,
        0.00395
      ],
      [
        0.0035000774,
        0.01487239,
        0.0039
      ],
      [
        0.0035000774,
        0.01487239,
        0.00395
      ],
      [
        0.0035088167,
        0.015718266,
        0.0039
      ],
      [
        0.0035088167,
        0.015718266,
        0.00395
      ],
      [
        0.0035119914,
        0.01545846,
        0.0039
      ],
      [
        0.0035119914,
        0.01545846,
        0.00395
      ],
      [
        0.003517638,
        0.014847731,
        0.0039
      ],
      [
        0.003517638,
        0.014847731,
        0.00395
      ],
      [
        0.0035220548,
        0.015743293,
        0.0039
      ],
      [
        0.0035220548,
        0.015743293,
        0.00395
      ],
      [
        0.0035223442,
        0.015440197,
        0.0039
      ],
      [
        0.0035223442,
        0.015440197,
        0.00395
      ],
      [
        0.0035320467,
        0.015759835,
        0.0039000004
      ],
      [
        0.0035320467,
        0.015759835,
        0.00395
      ],
      [
        0.0035356453,
        0.01542154,
        0.0039
      ],
      [
        0.0035356453,
        0.01542154,
        0.00395
      ],
      [
        0.0035439678,
        0.015777038,
        0.0039
      ],
      [
        0.0035439678,
        0.015777038,
        0.00395
      ],
      [
        0.00354523,
        0.014816553,
        0.0039
      ],
      [
        0.00354523,
        0.014816553,
        0.00395
      ],
      [
        0.0035562397,
        0.015397691,
        0.0039
      ],
      [
        0.0035562397,
        0.015397691,
        0.00395
      ],
      [
        0.0035639384,
        0.015800359,
        0.0039
      ],
      [
        0.0035639384,
        0.015800359,
        0.00395
      ],
      [
        0.0035759828,
        0.014788488,
        0.0039
      ],
      [
        0.0035759828,
        0.014788488,
        0.00395
      ],
      [
        0.003579039,
        0.015375941,
        0.0039
      ],
      [
        0.003579039,
        0.015375941,
        0.00395
      ],
      [
        0.003584678,
        0.0151012,
        0.0039
      ],
      [
        0.003584678,
        0.0151012,
        0.00395
      ],
      [
        0.003586059,
        0.015821652,
        0.0039
      ],
      [
        0.003586059,
        0.015821652,
        0.00395
      ],
      [
        0.0035887242,
        0.015069617,
        0.0039
      ],
      [
        0.0035887242,
        0.015069617,
        0.00395
      ],
      [
        0.0035957026,
        0.015038549,
        0.0039
      ],
      [
        0.0035957026,
        0.015038549,
        0.00395
      ],
      [
        0.00360383,
        0.015356491,
        0.0039
      ],
      [
        0.00360383,
        0.015356491,
        0.00395
      ],
      [
        0.0036055523,
        0.015008269,
        0.0039
      ],
      [
        0.0036055523,
        0.015008269,
        0.00395
      ],
      [
        0.0036095476,
        0.014763855,
        0.0039
      ],
      [
        0.0036095476,
        0.014763855,
        0.00395
      ],
      [
        0.0036101243,
        0.01584072,
        0.0039
      ],
      [
        0.0036101243,
        0.01584072,
        0.00395
      ],
      [
        0.0036181868,
        0.014979041,
        0.0039
      ],
      [
        0.0036181868,
        0.014979041,
        0.00395
      ],
      [
        0.0036303822,
        0.0153395245,
        0.0039
      ],
      [
        0.0036303822,
        0.0153395245,
        0.00395
      ],
      [
        0.003633304,
        0.015602396,
        0.0039
      ],
      [
        0.003633304,
        0.015602396,
        0.00395
      ],
      [
        0.0036333832,
        0.015611297,
        0.0039
      ],
      [
        0.0036333832,
        0.015611297,
        0.00395
      ],
      [
        0.003633496,
        0.014951121,
        0.0039
      ],
      [
        0.003633496,
        0.014951121,
        0.00395
      ],
      [
        0.0036336235,
        0.015593733,
        0.0039
      ],
      [
        0.0036336235,
        0.015593733,
        0.00395
      ],
      [
        0.003634918,
        0.015579149,
        0.0039
      ],
      [
        0.003634918,
        0.015579149,
        0.00395
      ],
      [
        0.003635351,
        0.015627496,
        0.0039
      ],
      [
        0.003635351,
        0.015627496,
        0.00395
      ],
      [
        0.0036359113,
        0.015857385,
        0.0039
      ],
      [
        0.0036359113,
        0.015857385,
        0.00395
      ],
      [
        0.0036377555,
        0.015564786,
        0.0039
      ],
      [
        0.0036377555,
        0.015564786,
        0.00395
      ],
      [
        0.003638981,
        0.015643403,
        0.0039
      ],
      [
        0.003638981,
        0.015643403,
        0.00395
      ],
      [
        0.0036421039,
        0.015550807,
        0.0039
      ],
      [
        0.0036421039,
        0.015550807,
        0.00395
      ],
      [
        0.0036442336,
        0.015658852,
        0.0039
      ],
      [
        0.0036442336,
        0.015658852,
        0.00395
      ],
      [
        0.0036455432,
        0.014742934,
        0.0039
      ],
      [
        0.0036455432,
        0.014742934,
        0.00395
      ],
      [
        0.0036462687,
        0.014934891,
        0.0039
      ],
      [
        0.0036462687,
        0.014934891,
        0.00395
      ],
      [
        0.0036479135,
        0.015537368,
        0.0039
      ],
      [
        0.0036479135,
        0.015537368,
        0.00395
      ],
      [
        0.0036504725,
        0.015328452,
        0.0039
      ],
      [
        0.0036504725,
        0.015328452,
        0.00395
      ],
      [
        0.003651053,
        0.015673677,
        0.0039
      ],
      [
        0.003651053,
        0.015673677,
        0.00395
      ],
      [
        0.0036551186,
        0.015524624,
        0.0039
      ],
      [
        0.0036551186,
        0.015524624,
        0.00395
      ],
      [
        0.0036593662,
        0.015687717,
        0.0039
      ],
      [
        0.0036593662,
        0.015687717,
        0.00395
      ],
      [
        0.0036631813,
        0.015871495,
        0.0039
      ],
      [
        0.0036631813,
        0.015871495,
        0.00395
      ],
      [
        0.003663638,
        0.015512717,
        0.0039
      ],
      [
        0.003663638,
        0.015512717,
        0.00395
      ],
      [
        0.0036657637,
        0.01491425,
        0.0039
      ],
      [
        0.0036657637,
        0.01491425,
        0.00395
      ],
      [
        0.0036690845,
        0.015700825,
        0.0039
      ],
      [
        0.0036690845,
        0.015700825,
        0.00395
      ],
      [
        0.0036728356,
        0.014729726,
        0.0039000004
      ],
      [
        0.0036728356,
        0.014729726,
        0.00395
      ],
      [
        0.0036733744,
        0.015501784,
        0.0039
      ],
      [
        0.0036733744,
        0.015501784,
        0.00395
      ],
      [
        0.0036799056,
        0.0154961115,
        0.0039
      ],
      [
        0.0036799056,
        0.0154961115,
        0.00395
      ],
      [
        0.003680104,
        0.015712857,
        0.0039
      ],
      [
        0.003680104,
        0.015712857,
        0.00395
      ],
      [
        0.0036823854,
        0.015879866,
        0.0039
      ],
      [
        0.0036823854,
        0.015879866,
        0.00395
      ],
      [
        0.0036842187,
        0.015312812,
        0.0039
      ],
      [
        0.0036842187,
        0.015312812,
        0.00395
      ],
      [
        0.0036868658,
        0.015490393,
        0.0039
      ],
      [
        0.0036868658,
        0.015490393,
        0.00395
      ],
      [
        0.0036873017,
        0.01489575,
        0.0039
      ],
      [
        0.0036873017,
        0.01489575,
        0.00395
      ],
      [
        0.0036923068,
        0.01572369,
        0.0039
      ],
      [
        0.0036923068,
        0.01572369,
        0.00395
      ],
      [
        0.003696721,
        0.015483704,
        0.0039
      ],
      [
        0.003696721,
        0.015483704,
        0.00395
      ],
      [
        0.0036990915,
        0.015729506,
        0.0039
      ],
      [
        0.0036990915,
        0.015729506,
        0.00395
      ],
      [
        0.0037106487,
        0.014879594,
        0.0039
      ],
      [
        0.0037106487,
        0.014879594,
        0.00395
      ],
      [
        0.0037128513,
        0.015474712,
        0.0039
      ],
      [
        0.0037128513,
        0.015474712,
        0.00395
      ],
      [
        0.003713348,
        0.015739728,
        0.0039
      ],
      [
        0.003713348,
        0.015739728,
        0.00395
      ],
      [
        0.0037174176,
        0.014713788,
        0.0039
      ],
      [
        0.0037174176,
        0.014713788,
        0.00395
      ],
      [
        0.0037290228,
        0.015748743,
        0.0039
      ],
      [
        0.0037290228,
        0.015748743,
        0.00395
      ],
      [
        0.003730098,
        0.015896812,
        0.0039
      ],
      [
        0.003730098,
        0.015896812,
        0.00395
      ],
      [
        0.003735551,
        0.014865956,
        0.0039
      ],
      [
        0.003735551,
        0.014865956,
        0.00395
      ],
      [
        0.003739525,
        0.015462673,
        0.0039
      ],
      [
        0.003739525,
        0.015462673,
        0.00395
      ],
      [
        0.0037414313,
        0.015292096,
        0.0039
      ],
      [
        0.0037414313,
        0.015292096,
        0.00395
      ],
      [
        0.0037478942,
        0.015757341,
        0.0039
      ],
      [
        0.0037478942,
        0.015757341,
        0.00395
      ],
      [
        0.0037543525,
        0.014857376,
        0.0039
      ],
      [
        0.0037543525,
        0.014857376,
        0.00395
      ],
      [
        0.0037710208,
        0.015765388,
        0.0039
      ],
      [
        0.0037710208,
        0.015765388,
        0.00395
      ],
      [
        0.0037767224,
        0.014698334,
        0.0039
      ],
      [
        0.0037767224,
        0.014698334,
        0.00395
      ],
      [
        0.0037841962,
        0.014845617,
        0.0039
      ],
      [
        0.0037841962,
        0.014845617,
        0.00395
      ],
      [
        0.0037902691,
        0.015911315,
        0.0039
      ],
      [
        0.0037902691,
        0.015911315,
        0.00395
      ],
      [
        0.0038000257,
        0.015772616,
        0.0039
      ],
      [
        0.0038000257,
        0.015772616,
        0.00395
      ],
      [
        0.003800889,
        0.015441298,
        0.0039
      ],
      [
        0.003800889,
        0.015441298,
        0.00395
      ],
      [
        0.0038240736,
        0.014834026,
        0.0039
      ],
      [
        0.0038240736,
        0.014834026,
        0.00395
      ],
      [
        0.0038371559,
        0.014688152,
        0.0039
      ],
      [
        0.0038371559,
        0.014688152,
        0.00395
      ],
      [
        0.0038448984,
        0.015779292,
        0.0039
      ],
      [
        0.0038448984,
        0.015779292,
        0.00395
      ],
      [
        0.003851658,
        0.015919209,
        0.0039
      ],
      [
        0.003851658,
        0.015919209,
        0.00395
      ],
      [
        0.003864846,
        0.014826142,
        0.0039
      ],
      [
        0.003864846,
        0.014826142,
        0.00395
      ],
      [
        0.0038818496,
        0.015253452,
        0.0039
      ],
      [
        0.0038818496,
        0.015253452,
        0.00395
      ],
      [
        0.0038982504,
        0.014683319,
        0.0039
      ],
      [
        0.0038982504,
        0.014683319,
        0.00395
      ],
      [
        0.003902289,
        0.015920732,
        0.0039000004
      ],
      [
        0.003902289,
        0.015920732,
        0.00395
      ],
      [
        0.0039061697,
        0.014822031,
        0.0039
      ],
      [
        0.0039061697,
        0.014822031,
        0.00395
      ],
      [
        0.0039088298,
        0.015782267,
        0.0039
      ],
      [
        0.0039088298,
        0.015782267,
        0.00395
      ],
      [
        0.0039190226,
        0.015410647,
        0.0039
      ],
      [
        0.0039190226,
        0.015410647,
        0.00395
      ],
      [
        0.0039382633,
        0.014821221,
        0.0039
      ],
      [
        0.0039382633,
        0.014821221,
        0.00395
      ],
      [
        0.0039431667,
        0.015920052,
        0.0039
      ],
      [
        0.0039431667,
        0.015920052,
        0.00395
      ],
      [
        0.0039456175,
        0.014682917,
        0.0039000004
      ],
      [
        0.0039456175,
        0.014682917,
        0.00395
      ],
      [
        0.003962429,
        0.015779832,
        0.0039
      ],
      [
        0.003962429,
        0.015779832,
        0.00395
      ],
      [
        0.0039859884,
        0.014683622,
        0.0039
      ],
      [
        0.0039859884,
        0.014683622,
        0.00395
      ],
      [
        0.0039912863,
        0.014823701,
        0.0039
      ],
      [
        0.0039912863,
        0.014823701,
        0.00395
      ],
      [
        0.003995852,
        0.015915314,
        0.0039
      ],
      [
        0.003995852,
        0.015915314,
        0.00395
      ],
      [
        0.004002831,
        0.015774077,
        0.0039
      ],
      [
        0.004002831,
        0.015774077,
        0.00395
      ],
      [
        0.004034664,
        0.015766356,
        0.0039
      ],
      [
        0.004034664,
        0.015766356,
        0.00395
      ],
      [
        0.004034972,
        0.014830035,
        0.0039
      ],
      [
        0.004034972,
        0.014830035,
        0.00395
      ],
      [
        0.004037944,
        0.014689,
        0.0039
      ],
      [
        0.004037944,
        0.014689,
        0.00395
      ],
      [
        0.0040479186,
        0.015905973,
        0.0039
      ],
      [
        0.0040479186,
        0.015905973,
        0.00395
      ],
      [
        0.004060469,
        0.015757369,
        0.0039
      ],
      [
        0.004060469,
        0.015757369,
        0.00395
      ],
      [
        0.004072014,
        0.014839161,
        0.0039
      ],
      [
        0.004072014,
        0.014839161,
        0.00395
      ],
      [
        0.0040819105,
        0.015747465,
        0.0039
      ],
      [
        0.0040819105,
        0.015747465,
        0.00395
      ],
      [
        0.0040820492,
        0.015369685,
        0.0039
      ],
      [
        0.0040820492,
        0.015369685,
        0.00395
      ],
      [
        0.0040891543,
        0.0146992905,
        0.0039
      ],
      [
        0.0040891543,
        0.0146992905,
        0.00395
      ],
      [
        0.0040952372,
        0.015194903,
        0.0039000004
      ],
      [
        0.0040952372,
        0.015194903,
        0.00395
      ],
      [
        0.0040985104,
        0.014848256,
        0.0039
      ],
      [
        0.0040985104,
        0.014848256,
        0.00395
      ],
      [
        0.004098965,
        0.015892098,
        0.0039
      ],
      [
        0.004098965,
        0.015892098,
        0.00395
      ],
      [
        0.0041001076,
        0.01573679,
        0.0039
      ],
      [
        0.0041001076,
        0.01573679,
        0.00395
      ],
      [
        0.004111469,
        0.015188485,
        0.0039
      ],
      [
        0.004111469,
        0.015188485,
        0.00395
      ],
      [
        0.0041144323,
        0.014854807,
        0.0039
      ],
      [
        0.0041144323,
        0.014854807,
        0.00395
      ],
      [
        0.0041158297,
        0.01572536,
        0.0039
      ],
      [
        0.0041158297,
        0.01572536,
        0.00395
      ],
      [
        0.004117696,
        0.015723838,
        0.0039
      ],
      [
        0.004117696,
        0.015723838,
        0.00395
      ],
      [
        0.0041326904,
        0.01571018,
        0.0039
      ],
      [
        0.0041326904,
        0.01571018,
        0.00395
      ],
      [
        0.0041332757,
        0.015178575,
        0.0039
      ],
      [
        0.0041332757,
        0.015178575,
        0.00395
      ],
      [
        0.004135645,
        0.014865238,
        0.0039
      ],
      [
        0.004135645,
        0.014865238,
        0.00395
      ],
      [
        0.0041373293,
        0.015878005,
        0.0039000004
      ],
      [
        0.0041373293,
        0.015878005,
        0.00395
      ],
      [
        0.004139154,
        0.014714401,
        0.0039
      ],
      [
        0.004139154,
        0.014714401,
        0.00395
      ],
      [
        0.004146954,
        0.015694264,
        0.0039
      ],
      [
        0.004146954,
        0.015694264,
        0.00395
      ],
      [
        0.0041540205,
        0.015166599,
        0.0039
      ],
      [
        0.0041540205,
        0.015166599,
        0.00395
      ],
      [
        0.0041556377,
        0.014877851,
        0.0039
      ],
      [
        0.0041556377,
        0.014877851,
        0.00395
      ],
      [
        0.0041572913,
        0.015869,
        0.0039
      ],
      [
        0.0041572913,
        0.015869,
        0.00395
      ],
      [
        0.004157539,
        0.015345234,
        0.0039
      ],
      [
        0.004157539,
        0.015345234,
        0.00395
      ],
      [
        0.0041595693,
        0.015676875,
        0.0039
      ],
      [
        0.0041595693,
        0.015676875,
        0.00395
      ],
      [
        0.0041707642,
        0.015657615,
        0.0039
      ],
      [
        0.0041707642,
        0.015657615,
        0.00395
      ],
      [
        0.0041735084,
        0.015152671,
        0.0039
      ],
      [
        0.0041735084,
        0.015152671,
        0.00395
      ],
      [
        0.004174187,
        0.014892505,
        0.0039
      ],
      [
        0.004174187,
        0.014892505,
        0.00395
      ],
      [
        0.004176549,
        0.014729577,
        0.0039
      ],
      [
        0.004176549,
        0.014729577,
        0.00395
      ],
      [
        0.0041806414,
        0.01563594,
        0.0039
      ],
      [
        0.0041806414,
        0.01563594,
        0.00395
      ],
      [
        0.004184357,
        0.01533423,
        0.0039
      ],
      [
        0.004184357,
        0.01533423,
        0.00395
      ],
      [
        0.004185651,
        0.015853982,
        0.0039
      ],
      [
        0.004185651,
        0.015853982,
        0.00395
      ],
      [
        0.004189162,
        0.015611107,
        0.0039
      ],
      [
        0.004189162,
        0.015611107,
        0.00395
      ],
      [
        0.0041910843,
        0.0149090355,
        0.0039
      ],
      [
        0.0041910843,
        0.0149090355,
        0.00395
      ],
      [
        0.004191555,
        0.015136921,
        0.0039
      ],
      [
        0.004191555,
        0.015136921,
        0.00395
      ],
      [
        0.0041961223,
        0.015582102,
        0.0039
      ],
      [
        0.0041961223,
        0.015582102,
        0.00395
      ],
      [
        0.0042007086,
        0.015551163,
        0.0039
      ],
      [
        0.0042007086,
        0.015551163,
        0.00395
      ],
      [
        0.0042014704,
        0.014741769,
        0.0039
      ],
      [
        0.0042014704,
        0.014741769,
        0.00395
      ],
      [
        0.0042020185,
        0.014922295,
        0.0039
      ],
      [
        0.0042020185,
        0.014922295,
        0.00395
      ],
      [
        0.0042034197,
        0.015124203,
        0.0039
      ],
      [
        0.0042034197,
        0.015124203,
        0.00395
      ],
      [
        0.004208326,
        0.015322641,
        0.0039
      ],
      [
        0.004208326,
        0.015322641,
        0.00395
      ],
      [
        0.0042085056,
        0.0149321705,
        0.0039
      ],
      [
        0.0042085056,
        0.0149321705,
        0.00395
      ],
      [
        0.0042100605,
        0.015114989,
        0.0039
      ],
      [
        0.0042100605,
        0.015114989,
        0.00395
      ],
      [
        0.0042124633,
        0.01583635,
        0.0039
      ],
      [
        0.0042124633,
        0.01583635,
        0.00395
      ],
      [
        0.004217118,
        0.014947196,
        0.0039
      ],
      [
        0.004217118,
        0.014947196,
        0.00395
      ],
      [
        0.0042183567,
        0.015100551,
        0.0039
      ],
      [
        0.0042183567,
        0.015100551,
        0.00395
      ],
      [
        0.004224207,
        0.014962996,
        0.0039
      ],
      [
        0.004224207,
        0.014962996,
        0.00395
      ],
      [
        0.004225112,
        0.015085331,
        0.0039
      ],
      [
        0.004225112,
        0.015085331,
        0.00395
      ],
      [
        0.0042297025,
        0.01497942,
        0.0039
      ],
      [
        0.0042297025,
        0.01497942,
        0.00395
      ],
      [
        0.004230255,
        0.015069493,
        0.0039
      ],
      [
        0.004230255,
        0.015069493,
        0.00395
      ],
      [
        0.0042335517,
        0.014996305,
        0.0039
      ],
      [
        0.0042335517,
        0.014996305,
        0.00395
      ],
      [
        0.004233729,
        0.015053208,
        0.0039
      ],
      [
        0.004233729,
        0.015053208,
        0.00395
      ],
      [
        0.004234264,
        0.0147612095,
        0.0039
      ],
      [
        0.004234264,
        0.0147612095,
        0.00395
      ],
      [
        0.0042354977,
        0.01503665,
        0.0039
      ],
      [
        0.0042354977,
        0.01503665,
        0.00395
      ],
      [
        0.004235716,
        0.015013488,
        0.0039
      ],
      [
        0.004235716,
        0.015013488,
        0.00395
      ],
      [
        0.004235965,
        0.015025292,
        0.0039000004
      ],
      [
        0.004235965,
        0.015025292,
        0.00395
      ],
      [
        0.004237488,
        0.01581626,
        0.0039
      ],
      [
        0.004237488,
        0.01581626,
        0.00395
      ],
      [
        0.0042401743,
        0.01530469,
        0.0039
      ],
      [
        0.0042401743,
        0.01530469,
        0.00395
      ],
      [
        0.004260501,
        0.015793895,
        0.0039
      ],
      [
        0.004260501,
        0.015793895,
        0.00395
      ],
      [
        0.0042648246,
        0.014784,
        0.0039
      ],
      [
        0.0042648246,
        0.014784,
        0.00395
      ],
      [
        0.004270071,
        0.015283648,
        0.0039
      ],
      [
        0.004270071,
        0.015283648,
        0.00395
      ],
      [
        0.0042812955,
        0.015769454,
        0.0039
      ],
      [
        0.0042812955,
        0.015769454,
        0.00395
      ],
      [
        0.0042928113,
        0.014809886,
        0.0039
      ],
      [
        0.0042928113,
        0.014809886,
        0.00395
      ],
      [
        0.0042939982,
        0.015751638,
        0.0039
      ],
      [
        0.0042939982,
        0.015751638,
        0.00395
      ],
      [
        0.0042977165,
        0.015259725,
        0.0039
      ],
      [
        0.0042977165,
        0.015259725,
        0.00395
      ],
      [
        0.0043077385,
        0.01572872,
        0.0039
      ],
      [
        0.0043077385,
        0.01572872,
        0.00395
      ],
      [
        0.004317912,
        0.014838579,
        0.0039
      ],
      [
        0.004317912,
        0.014838579,
        0.00395
      ],
      [
        0.004322835,
        0.015233162,
        0.0039
      ],
      [
        0.004322835,
        0.015233162,
        0.00395
      ],
      [
        0.0043238634,
        0.01569572,
        0.0039
      ],
      [
        0.0043238634,
        0.01569572,
        0.00395
      ],
      [
        0.004333722,
        0.01486135,
        0.0039000004
      ],
      [
        0.004333722,
        0.01486135,
        0.00395
      ],
      [
        0.0043364544,
        0.015661217,
        0.0039
      ],
      [
        0.0043364544,
        0.015661217,
        0.00395
      ],
      [
        0.004339126,
        0.015212154,
        0.0039
      ],
      [
        0.004339126,
        0.015212154,
        0.00395
      ],
      [
        0.004344284,
        0.014878911,
        0.0039
      ],
      [
        0.004344284,
        0.014878911,
        0.00395
      ],
      [
        0.0043453737,
        0.015625589,
        0.0039
      ],
      [
        0.0043453737,
        0.015625589,
        0.00395
      ],
      [
        0.004349136,
        0.015195635,
        0.0039
      ],
      [
        0.004349136,
        0.015195635,
        0.00395
      ],
      [
        0.004350523,
        0.015589223,
        0.0039
      ],
      [
        0.004350523,
        0.015589223,
        0.00395
      ],
      [
        0.0043518664,
        0.01556254,
        0.0039
      ],
      [
        0.0043518664,
        0.01556254,
        0.00395
      ],
      [
        0.0043583913,
        0.014905403,
        0.0039
      ],
      [
        0.0043583913,
        0.014905403,
        0.00395
      ],
      [
        0.004362045,
        0.015170411,
        0.0039
      ],
      [
        0.004362045,
        0.015170411,
        0.00395
      ],
      [
        0.0043699197,
        0.014933116,
        0.0039
      ],
      [
        0.0043699197,
        0.014933116,
        0.00395
      ],
      [
        0.004372497,
        0.015144073,
        0.0039
      ],
      [
        0.004372497,
        0.015144073,
        0.00395
      ],
      [
        0.0043787654,
        0.014961797,
        0.0039
      ],
      [
        0.0043787654,
        0.014961797,
        0.00395
      ],
      [
        0.004380398,
        0.015116861,
        0.0039
      ],
      [
        0.004380398,
        0.015116861,
        0.00395
      ],
      [
        0.0043848483,
        0.014991188,
        0.0039
      ],
      [
        0.0043848483,
        0.014991188,
        0.00395
      ],
      [
        0.004385676,
        0.015089022,
        0.0039
      ],
      [
        0.004385676,
        0.015089022,
        0.00395
      ],
      [
        0.004388114,
        0.015021024,
        0.0039
      ],
      [
        0.004388114,
        0.015021024,
        0.00395
      ],
      [
        0.004388283,
        0.015060806,
        0.0039
      ],
      [
        0.004388283,
        0.015060806,
        0.00395
      ],
      [
        0.0043886346,
        0.015041482,
        0.0039
      ],
      [
        0.0043886346,
        0.015041482,
        0.00395
      ]
    ]
  }
}
