{
  "bounds": {
    "center": [
      -0.0088,
      0.0012160765,
      0.0005
    ],
    "size": [
      0.001,
      0.001,
      0.001
    ]
  },
  "primitives": [
    {
      "Box": {
        "center": [
          -0.0088,
          0.0012160765,
          0.0005
        ],
        "size": [
          0.001,
          0.001,
          0.001
        ]
      }
    },
    {
      "Sphere": {
        "center": [
          -0.0088,
          0.0012160765,
          0.0005
        ],
        "radius": 0.00068373996
      }
    },
    {
      "Cylinder": {
        "center": [
          -0.0088,
          0.0012160765,
          0.0005
        ],
        "axis": "X",
        "radius": 0.0006363962,
        "height": 0.001
      }
    },
    {
      "Capsule": {
        "a": [
          -0.00905,
          0.0012160765,
          0.0005
        ],
        "b": [
          -0.00855,
          0.0012160765,
          0.0005
        ],
        "radius": 0.0006363962
      }
    },
    {
      "Cylinder": {
        "center": [
          -0.0088,
          0.0012160765,
          0.0005
        ],
        "axis": "Y",
        "radius": 0.00051478174,
        "height": 0.001
      }
    },
    {
      "Capsule": {
        "a": [
          -0.0088,
          0.00076607656,
          0.0005
        ],
        "b": [
          -0.0088,
          0.0016660766,
          0.0005
        ],
        "radius": 0.00051478174
      }
    },
    {
      "Cylinder": {
        "center": [
          -0.0088,
          0.0012160765,
          0.0005
        ],
        "axis": "Z",
        "radius": 0.0005147818,
        "height": 0.001
      }
    },
    {
      "Capsule": {
        "a": [
          -0.0088,
          0.0012160765,
          5e-05
        ],
        "b": [
          -0.0088,
          0.0012160765,
          0.00095
        ],
        "radius": 0.0005147818
      }
    }
  ],
  "compounds": [
    {
      "partition_axis": "X",
      "parts": [
        {
          "center": [
            -0.0088,
            0.0012160765,
            0.0005
          ],
          "size": [
            0.001,
            0.001,
            0.001
          ]
        },
        {
          "center": [
            -0.0088,
            0.0016660766,
            0.0005
          ],
          "size": [
            0.001,
            0.001,
            0.001
          ]
        },
        {
          "center": [
            -0.008797634,
            0.00076607656,
            0.0005
          ],
          "size": [
            0.001,
            0.001,
            0.001
          ]
        },
        {
          "center": [
            -0.00855,
            0.0012160765,
            0.0005
          ],
          "size": [
            0.001,
            0.001,
            0.001
          ]
        }
      ],
      "quality": {
        "source_triangle_count": 140,
        "covered_triangle_count": 140,
        "conservative_volume": 4.0000008e-09,
        "bounds_volume_ratio": 4.0,
        "generation_path": "Exact"
      }
    }
  ],
  "convex_hull": {
    "points": [
      [
        -0.00905,
        0.001025461,
        5e-05
      ],
      [
        -0.00905,
        0.001025461,
        0.00095
      ],
      [
        -0.00905,
        0.001407193,
        5e-05
      ],
      [
        -0.00905,
        0.001407193,
        0.00095
      ],
      [
        -0.00905,
        0.0016660766,
        5e-05
      ],
      [
        -0.00905,
        0.0016660766,
        0.00095
      ],
      [
        -0.009045268,
        0.00076607656,
        5e-05
      ],
      [
        -0.009045268,
        0.00076607656,
        0.00095
      ],
      [
        -0.009,
        0.001025461,
        5e-05
      ],
      [
        -0.009,
        0.001025461,
        0.00095
      ],
      [
        -0.009,
        0.001407193,
        5e-05
      ],
      [
        -0.009,
        0.001407193,
        0.00095
      ],
      [
        -0.008979363,
        0.0010265799,
        5e-05
      ],
      [
        -0.008979363,
        0.0010265799,
        0.00095
      ],
      [
        -0.008979363,
        0.0014060742,
        5e-05
      ],
      [
        -0.008979363,
        0.0014060742,
        0.00095
      ],
      [
        -0.008958969,
        0.0010299233,
        5e-05
      ],
      [
        -0.008958969,
        0.0010299233,
        0.00095
      ],
      [
        -0.008958969,
        0.0014027307,
        5e-05
      ],
      [
        -0.008958969,
        0.0014027307,
        0.00095
      ],
      [
        -0.008939057,
        0.0010354522,
        5e-05
      ],
      [
        -0.008939057,
        0.0010354522,
        0.00095
      ],
      [
        -0.008939057,
        0.0013972018,
        5e-05
      ],
      [
        -0.008939057,
        0.0013972018,
        0.00095
      ],
      [
        -0.008919857,
        0.0010431017,
        5e-05
      ],
      [
        -0.008919857,
        0.0010431017,
        0.00095
      ],
      [
        -0.008919857,
        0.0013895523,
        5e-05
      ],
      [
        -0.008919857,
        0.0013895523,
        0.00095
      ],
      [
        -0.008901598,
        0.001052782,
        5e-05
      ],
      [
        -0.008901598,
        0.001052782,
        0.00095
      ],
      [
        -0.008901598,
        0.0013798719,
        5e-05
      ],
      [
        -0.008901598,
        0.0013798719,
        0.00095
      ],
      [
        -0.008884493,
        0.0010643799,
        5e-05
      ],
      [
        -0.008884493,
        0.0010643799,
        0.00095
      ],
      [
        -0.008884493,
        0.0013682741,
        5e-05
      ],
      [
        -0.008884493,
        0.0013682741,
        0.00095
      ],
      [
        -0.008868742,
        0.0010777592,
        5e-05
      ],
      [
        -0.008868742,
        0.0010777592,
        0.00095
      ],
      [
        -0.008868742,
        0.0013548948,
        5e-05
      ],
      [
        -0.008868742,
        0.0013548948,
        0.00095
      ],
      [
        -0.008854529,
        0.0010927629,
        5e-05
      ],
      [
        -0.008854529,
        0.0010927629,
        0.00095
      ],
      [
        -0.008854529,
        0.001339891,
        5e-05
      ],
      [
        -0.008854529,
        0.001339891,
        0.00095
      ],
      [
        -0.008842022,
        0.0011092154,
        5e-05
      ],
      [
        -0.008842022,
        0.0011092154,
        0.00095
      ],
      [
        -0.008842022,
        0.0013234385,
        5e-05
      ],
      [
        -0.008842022,
        0.0013234385,
        0.00095
      ],
      [
        -0.008831368,
        0.0011269237,
        5e-05
      ],
      [
        -0.008831368,
        0.0011269237,
        0.00095
      ],
      [
        -0.008831368,
        0.0013057302,
        5e-05
      ],
      [
        -0.008831368,
        0.0013057302,
        0.00095
      ],
      [
        -0.00882269,
        0.0011456802,
        5e-05
      ],
      [
        -0.00882269,
        0.0011456802,
        0.00095
      ],
      [
        -0.00882269,
        0.0012869738,
        5e-05
      ],
      [
        -0.00882269,
        0.0012869738,
        0.00095
      ],
      [
        -0.008816091,
        0.001165265,
        5e-05
      ],
      [
        -0.008816091,
        0.001165265,
        0.00095
      ],
      [
        -0.008816091,
        0.001267389,
        5e-05
      ],
      [
        -0.008816091,
        0.001267389,
        0.00095
      ],
      [
        -0.008811648,
        0.0011854484,
        5e-05
      ],
      [
        -0.008811648,
        0.0011854484,
        0.00095
      ],
      [
        -0.008811648,
        0.0012472057,
        5e-05
      ],
      [
        -0.008811648,
        0.0012472057,
        0.00095
      ],
      [
        -0.008809414,
        0.0012059937,
        5e-05
      ],
      [
        -0.008809414,
        0.0012059937,
        0.00095
      ],
      [
        -0.008809414,
        0.0012266603,
        5e-05
      ],
      [
        -0.008809414,
        0.0012266603,
        0.00095
      ],
      [
        -0.00855,
        0.00076607656,
        5e-05
      ],
      [
        -0.00855,
        0.00076607656,
        0.00095
      ],
      [
        -0.00855,
        0.0016660766,
        5e-05
      ],
      [
        -0.00855,
        0.0016660766,
        0.00095
      ]
    ]
  }
}
