{
  "bounds": {
    "center": [
      0.0,
      -0.0125,
      0.0
    ],
    "size": [
      0.03693003,
      0.025,
      0.036984272
    ]
  },
  "primitives": [
    {
      "Box": {
        "center": [
          0.0,
          -0.0125,
          0.0
        ],
        "size": [
          0.03693003,
          0.025,
          0.036984272
        ]
      }
    },
    {
      "Sphere": {
        "center": [
          0.0,
          -0.0125,
          0.0
        ],
        "radius": 0.022320598
      }
    },
    {
      "Cylinder": {
        "center": [
          0.0,
          -0.0125,
          0.0
        ],
        "axis": "X",
        "radius": 0.022320598,
        "height": 0.03693003
      }
    },
    {
      "Capsule": {
        "a": [
          -0.018465014,
          -0.0125,
          0.0
        ],
        "b": [
          0.018465014,
          -0.0125,
          0.0
        ],
        "radius": 0.022320598
      }
    },
    {
      "Cylinder": {
        "center": [
          0.0,
          -0.0125,
          0.0
        ],
        "axis": "Y",
        "radius": 0.018492136,
        "height": 0.025
      }
    },
    {
      "Capsule": {
        "a": [
          0.0,
          -0.025,
          0.0
        ],
        "b": [
          0.0,
          0.0,
          0.0
        ],
        "radius": 0.018492136
      }
    },
    {
      "Cylinder": {
        "center": [
          0.0,
          -0.0125,
          0.0
        ],
        "axis": "Z",
        "radius": 0.022298133,
        "height": 0.036984272
      }
    },
    {
      "Capsule": {
        "a": [
          0.0,
          -0.0125,
          -0.018492136
        ],
        "b": [
          0.0,
          -0.0125,
          0.018492136
        ],
        "radius": 0.022298133
      }
    }
  ],
  "compounds": [
    {
      "partition_axis": "Z",
      "parts": [
        {
          "center": [
            0.0,
            -0.025,
            0.0
          ],
          "size": [
            0.03693003,
            0.001,
            0.036984272
          ]
        },
        {
          "center": [
            0.0,
            -0.0125,
            0.0
          ],
          "size": [
            0.032935895,
            0.025,
            0.03298427
          ]
        },
        {
          "center": [
            0.0,
            -0.0125,
            0.0
          ],
          "size": [
            0.03693003,
            0.025,
            0.036984272
          ]
        },
        {
          "center": [
            0.0,
            0.0,
            0.0
          ],
          "size": [
            0.03693003,
            0.001,
            0.036984272
          ]
        }
      ],
      "quality": {
        "source_triangle_count": 464,
        "covered_triangle_count": 464,
        "conservative_volume": 6.4036576e-05,
        "bounds_volume_ratio": 1.875389,
        "generation_path": "Exact"
      }
    }
  ],
  "convex_hull": {
    "points": [
      [
        -0.018465014,
        -0.025,
        -0.0010011441
      ],
      [
        -0.018465014,
        -0.025,
        0.0010011441
      ],
      [
        -0.018465014,
        0.0,
        -0.0010011441
      ],
      [
        -0.018465014,
        0.0,
        0.0010011441
      ],
      [
        -0.01824853,
        -0.025,
        -0.0029916945
      ],
      [
        -0.01824853,
        -0.025,
        0.0029916945
      ],
      [
        -0.01824853,
        0.0,
        -0.0029916945
      ],
      [
        -0.01824853,
        0.0,
        0.0029916945
      ],
      [
        -0.017818097,
        -0.025,
        -0.00494717
      ],
      [
        -0.017818097,
        -0.025,
        0.00494717
      ],
      [
        -0.017818097,
        0.0,
        -0.00494717
      ],
      [
        -0.017818097,
        0.0,
        0.00494717
      ],
      [
        -0.017178763,
        -0.025,
        -0.006844645
      ],
      [
        -0.017178763,
        -0.025,
        0.006844645
      ],
      [
        -0.017178763,
        0.0,
        -0.006844645
      ],
      [
        -0.017178763,
        0.0,
        0.006844645
      ],
      [
        -0.016467948,
        -0.025,
        -0.0008928662
      ],
      [
        -0.016467948,
        -0.025,
        0.0008928662
      ],
      [
        -0.016467948,
        0.0,
        -0.0008928662
      ],
      [
        -0.016467948,
        0.0,
        0.0008928662
      ],
      [
        -0.016338024,
        -0.025,
        -0.008661873
      ],
      [
        -0.016338024,
        -0.025,
        0.008661873
      ],
      [
        -0.016338024,
        0.0,
        -0.008661873
      ],
      [
        -0.016338024,
        0.0,
        0.008661873
      ],
      [
        -0.016274877,
        -0.025,
        -0.0026681307
      ],
      [
        -0.016274877,
        -0.025,
        0.0026681307
      ],
      [
        -0.016274877,
        0.0,
        -0.0026681307
      ],
      [
        -0.016274877,
        0.0,
        0.0026681307
      ],
      [
        -0.015890997,
        -0.025,
        -0.0044121137
      ],
      [
        -0.015890997,
        -0.025,
        0.0044121137
      ],
      [
        -0.015890997,
        0.0,
        -0.0044121137
      ],
      [
        -0.015890997,
        0.0,
        0.0044121137
      ],
      [
        -0.01532081,
        -0.025,
        -0.0061043687
      ],
      [
        -0.01532081,
        -0.025,
        0.0061043687
      ],
      [
        -0.01532081,
        0.0,
        -0.0061043687
      ],
      [
        -0.01532081,
        0.0,
        0.0061043687
      ],
      [
        -0.015305737,
        -0.025,
        -0.010377547
      ],
      [
        -0.015305737,
        -0.025,
        0.010377547
      ],
      [
        -0.015305737,
        0.0,
        -0.010377547
      ],
      [
        -0.015305737,
        0.0,
        0.010377547
      ],
      [
        -0.014571,
        -0.025,
        -0.0077250553
      ],
      [
        -0.014571,
        -0.025,
        0.0077250553
      ],
      [
        -0.014571,
        0.0,
        -0.0077250553
      ],
      [
        -0.014571,
        0.0,
        0.0077250553
      ],
      [
        -0.0140940035,
        -0.025,
        -0.011971555
      ],
      [
        -0.0140940035,
        -0.025,
        0.011971555
      ],
      [
        -0.0140940035,
        0.0,
        -0.011971555
      ],
      [
        -0.0140940035,
        0.0,
        0.011971555
      ],
      [
        -0.013650359,
        -0.025,
        -0.009255173
      ],
      [
        -0.013650359,
        -0.025,
        0.009255173
      ],
      [
        -0.013650359,
        0.0,
        -0.009255173
      ],
      [
        -0.013650359,
        0.0,
        0.009255173
      ],
      [
        -0.012717032,
        -0.025,
        -0.013425207
      ],
      [
        -0.012717032,
        -0.025,
        0.013425207
      ],
      [
        -0.012717032,
        0.0,
        -0.013425207
      ],
      [
        -0.012717032,
        0.0,
        0.013425207
      ],
      [
        -0.01256968,
        -0.025,
        -0.010676783
      ],
      [
        -0.01256968,
        -0.025,
        0.010676783
      ],
      [
        -0.01256968,
        0.0,
        -0.010676783
      ],
      [
        -0.01256968,
        0.0,
        0.010676783
      ],
      [
        -0.011341632,
        -0.025,
        -0.011973216
      ],
      [
        -0.011341632,
        -0.025,
        0.011973216
      ],
      [
        -0.011341632,
        0.0,
        -0.011973216
      ],
      [
        -0.011341632,
        0.0,
        0.011973216
      ],
      [
        -0.011190964,
        -0.025,
        -0.014721461
      ],
      [
        -0.011190964,
        -0.025,
        0.014721461
      ],
      [
        -0.011190964,
        0.0,
        -0.014721461
      ],
      [
        -0.011190964,
        0.0,
        0.014721461
      ],
      [
        -0.009980615,
        -0.025,
        -0.013129274
      ],
      [
        -0.009980615,
        -0.025,
        0.013129274
      ],
      [
        -0.009980615,
        0.0,
        -0.013129274
      ],
      [
        -0.009980615,
        0.0,
        0.013129274
      ],
      [
        -0.009533692,
        -0.025,
        -0.015845118
      ],
      [
        -0.009533692,
        -0.025,
        0.015845118
      ],
      [
        -0.009533692,
        0.0,
        -0.015845118
      ],
      [
        -0.009533692,
        0.0,
        0.015845118
      ],
      [
        -0.008502584,
        -0.025,
        -0.014131404
      ],
      [
        -0.008502584,
        -0.025,
        0.014131404
      ],
      [
        -0.008502584,
        0.0,
        -0.014131404
      ],
      [
        -0.008502584,
        0.0,
        0.014131404
      ],
      [
        -0.0077646463,
        -0.025,
        -0.016783008
      ],
      [
        -0.0077646463,
        -0.025,
        0.016783008
      ],
      [
        -0.0077646463,
        0.0,
        -0.016783008
      ],
      [
        -0.0077646463,
        0.0,
        0.016783008
      ],
      [
        -0.006924868,
        -0.025,
        -0.014967857
      ],
      [
        -0.006924868,
        -0.025,
        0.014967857
      ],
      [
        -0.006924868,
        0.0,
        -0.014967857
      ],
      [
        -0.006924868,
        0.0,
        0.014967857
      ],
      [
        -0.005904567,
        -0.025,
        -0.01752413
      ],
      [
        -0.005904567,
        -0.025,
        0.01752413
      ],
      [
        -0.005904567,
        0.0,
        -0.01752413
      ],
      [
        -0.005904567,
        0.0,
        0.01752413
      ],
      [
        -0.005265964,
        -0.025,
        -0.015628824
      ],
      [
        -0.005265964,
        -0.025,
        0.015628824
      ],
      [
        -0.005265964,
        0.0,
        -0.015628824
      ],
      [
        -0.005265964,
        0.0,
        0.015628824
      ],
      [
        -0.0039752624,
        -0.025,
        -0.0180598
      ],
      [
        -0.0039752624,
        -0.025,
        0.0180598
      ],
      [
        -0.0039752624,
        0.0,
        -0.0180598
      ],
      [
        -0.0039752624,
        0.0,
        0.0180598
      ],
      [
        -0.0035453215,
        -0.025,
        -0.016106559
      ],
      [
        -0.0035453215,
        -0.025,
        0.016106559
      ],
      [
        -0.0035453215,
        0.0,
        -0.016106559
      ],
      [
        -0.0035453215,
        0.0,
        0.016106559
      ],
      [
        -0.0019993514,
        -0.025,
        -0.018383734
      ],
      [
        -0.0019993514,
        -0.025,
        0.018383734
      ],
      [
        -0.0019993514,
        0.0,
        -0.018383734
      ],
      [
        -0.0019993514,
        0.0,
        0.018383734
      ],
      [
        -0.0017831135,
        -0.025,
        -0.016395457
      ],
      [
        -0.0017831135,
        -0.025,
        0.016395457
      ],
      [
        -0.0017831135,
        0.0,
        -0.016395457
      ],
      [
        -0.0017831135,
        0.0,
        0.016395457
      ],
      [
        0.0,
        -0.025,
        0.016492136
      ],
      [
        0.0,
        -0.025,
        0.018492136
      ],
      [
        0.0,
        0.0,
        0.016492136
      ],
      [
        0.0,
        0.0,
        0.018492136
      ],
      [
        2.0197042e-18,
        -0.025,
        -0.016492136
      ],
      [
        2.2646334e-18,
        0.0,
        -0.018492136
      ],
      [
        6.059112e-18,
        0.0,
        -0.016492136
      ],
      [
        6.7939003e-18,
        -0.025,
        -0.018492136
      ],
      [
        0.0017831135,
        -0.025,
        -0.016395457
      ],
      [
        0.0017831135,
        -0.025,
        0.016395457
      ],
      [
        0.0017831135,
        0.0,
        -0.016395457
      ],
      [
        0.0017831135,
        0.0,
        0.016395457
      ],
      [
        0.0019993514,
        -0.025,
        -0.018383734
      ],
      [
        0.0019993514,
        -0.025,
        0.018383734
      ],
      [
        0.0019993514,
        0.0,
        -0.018383734
      ],
      [
        0.0019993514,
        0.0,
        0.018383734
      ],
      [
        0.0035453215,
        -0.025,
        -0.016106559
      ],
      [
        0.0035453215,
        -0.025,
        0.016106559
      ],
      [
        0.0035453215,
        0.0,
        -0.016106559
      ],
      [
        0.0035453215,
        0.0,
        0.016106559
      ],
      [
        0.0039752624,
        -0.025,
        -0.0180598
      ],
      [
        0.0039752624,
        -0.025,
        0.0180598
      ],
      [
        0.0039752624,
        0.0,
        -0.0180598
      ],
      [
        0.0039752624,
        0.0,
        0.0180598
      ],
      [
        0.005265964,
        -0.025,
        -0.015628824
      ],
      [
        0.005265964,
        -0.025,
        0.015628824
      ],
      [
        0.005265964,
        0.0,
        -0.015628824
      ],
      [
        0.005265964,
        0.0,
        0.015628824
      ],
      [
        0.005904567,
        -0.025,
        -0.01752413
      ],
      [
        0.005904567,
        -0.025,
        0.01752413
      ],
      [
        0.005904567,
        0.0,
        -0.01752413
      ],
      [
        0.005904567,
        0.0,
        0.01752413
      ],
      [
        0.006924868,
        -0.025,
        -0.014967857
      ],
      [
        0.006924868,
        -0.025,
        0.014967857
      ],
      [
        0.006924868,
        0.0,
        -0.014967857
      ],
      [
        0.006924868,
        0.0,
        0.014967857
      ],
      [
        0.0077646463,
        -0.025,
        -0.016783008
      ],
      [
        0.0077646463,
        -0.025,
        0.016783008
      ],
      [
        0.0077646463,
        0.0,
        -0.016783008
      ],
      [
        0.0077646463,
        0.0,
        0.016783008
      ],
      [
        0.008502584,
        -0.025,
        -0.014131404
      ],
      [
        0.008502584,
        -0.025,
        0.014131404
      ],
      [
        0.008502584,
        0.0,
        -0.014131404
      ],
      [
        0.008502584,
        0.0,
        0.014131404
      ],
      [
        0.009533692,
        -0.025,
        -0.015845118
      ],
      [
        0.009533692,
        -0.025,
        0.015845118
      ],
      [
        0.009533692,
        0.0,
        -0.015845118
      ],
      [
        0.009533692,
        0.0,
        0.015845118
      ],
      [
        0.009980615,
        -0.025,
        -0.013129274
      ],
      [
        0.009980615,
        -0.025,
        0.013129274
      ],
      [
        0.009980615,
        0.0,
        -0.013129274
      ],
      [
        0.009980615,
        0.0,
        0.013129274
      ],
      [
        0.011190964,
        -0.025,
        -0.014721461
      ],
      [
        0.011190964,
        -0.025,
        0.014721461
      ],
      [
        0.011190964,
        0.0,
        -0.014721461
      ],
      [
        0.011190964,
        0.0,
        0.014721461
      ],
      [
        0.011341632,
        -0.025,
        -0.011973216
      ],
      [
        0.011341632,
        -0.025,
        0.011973216
      ],
      [
        0.011341632,
        0.0,
        -0.011973216
      ],
      [
        0.011341632,
        0.0,
        0.011973216
      ],
      [
        0.01256968,
        -0.025,
        -0.010676783
      ],
      [
        0.01256968,
        -0.025,
        0.010676783
      ],
      [
        0.01256968,
        0.0,
        -0.010676783
      ],
      [
        0.01256968,
        0.0,
        0.010676783
      ],
      [
        0.012717032,
        -0.025,
        -0.013425207
      ],
      [
        0.012717032,
        -0.025,
        0.013425207
      ],
      [
        0.012717032,
        0.0,
        -0.013425207
      ],
      [
        0.012717032,
        0.0,
        0.013425207
      ],
      [
        0.013650359,
        -0.025,
        -0.009255173
      ],
      [
        0.013650359,
        -0.025,
        0.009255173
      ],
      [
        0.013650359,
        0.0,
        -0.009255173
      ],
      [
        0.013650359,
        0.0,
        0.009255173
      ],
      [
        0.0140940035,
        -0.025,
        -0.011971555
      ],
      [
        0.0140940035,
        -0.025,
        0.011971555
      ],
      [
        0.0140940035,
        0.0,
        -0.011971555
      ],
      [
        0.0140940035,
        0.0,
        0.011971555
      ],
      [
        0.014571,
        -0.025,
        -0.0077250553
      ],
      [
        0.014571,
        -0.025,
        0.0077250553
      ],
      [
        0.014571,
        0.0,
        -0.0077250553
      ],
      [
        0.014571,
        0.0,
        0.0077250553
      ],
      [
        0.015305737,
        -0.025,
        -0.010377547
      ],
      [
        0.015305737,
        -0.025,
        0.010377547
      ],
      [
        0.015305737,
        0.0,
        -0.010377547
      ],
      [
        0.015305737,
        0.0,
        0.010377547
      ],
      [
        0.01532081,
        -0.025,
        -0.0061043687
      ],
      [
        0.01532081,
        -0.025,
        0.0061043687
      ],
      [
        0.01532081,
        0.0,
        -0.0061043687
      ],
      [
        0.01532081,
        0.0,
        0.0061043687
      ],
      [
        0.015890997,
        -0.025,
        -0.0044121137
      ],
      [
        0.015890997,
        -0.025,
        0.0044121137
      ],
      [
        0.015890997,
        0.0,
        -0.0044121137
      ],
      [
        0.015890997,
        0.0,
        0.0044121137
      ],
      [
        0.016274877,
        -0.025,
        -0.0026681307
      ],
      [
        0.016274877,
        -0.025,
        0.0026681307
      ],
      [
        0.016274877,
        0.0,
        -0.0026681307
      ],
      [
        0.016274877,
        0.0,
        0.0026681307
      ],
      [
        0.016338024,
        -0.025,
        -0.008661873
      ],
      [
        0.016338024,
        -0.025,
        0.008661873
      ],
      [
        0.016338024,
        0.0,
        -0.008661873
      ],
      [
        0.016338024,
        0.0,
        0.008661873
      ],
      [
        0.016467948,
        -0.025,
        -0.0008928662
      ],
      [
        0.016467948,
        -0.025,
        0.0008928662
      ],
      [
        0.016467948,
        0.0,
        -0.0008928662
      ],
      [
        0.016467948,
        0.0,
        0.0008928662
      ],
      [
        0.017178763,
        -0.025,
        -0.006844645
      ],
      [
        0.017178763,
        -0.025,
        0.006844645
      ],
      [
        0.017178763,
        0.0,
        -0.006844645
      ],
      [
        0.017178763,
        0.0,
        0.006844645
      ],
      [
        0.017818097,
        -0.025,
        -0.00494717
      ],
      [
        0.017818097,
        -0.025,
        0.00494717
      ],
      [
        0.017818097,
        0.0,
        -0.00494717
      ],
      [
        0.017818097,
        0.0,
        0.00494717
      ],
      [
        0.01824853,
        -0.025,
        -0.0029916945
      ],
      [
        0.01824853,
        -0.025,
        0.0029916945
      ],
      [
        0.01824853,
        0.0,
        -0.0029916945
      ],
      [
        0.01824853,
        0.0,
        0.0029916945
      ],
      [
        0.018465014,
        -0.025,
        -0.0010011441
      ],
      [
        0.018465014,
        -0.025,
        0.0010011441
      ],
      [
        0.018465014,
        0.0,
        -0.0010011441
      ],
      [
        0.018465014,
        0.0,
        0.0010011441
      ]
    ]
  }
}
